setup.py
vsieve.py
vsieve.egg-info/PKG-INFO
vsieve.egg-info/SOURCES.txt
vsieve.egg-info/dependency_links.txt
vsieve.egg-info/top_level.txt