Metadata-Version: 1.1
Name: vsieve
Version: 1.0.1
Summary: Sieve of Eratosthenes for vector tuples
Home-page: https://gist.github.com/outofmbufs/87a0d260ad4e017c96e2
Author: Neil Webber
Author-email: nw@neilwebber.com
License: MIT
Platform: UNKNOWN
Classifier: Development Status :: 5 - Production/Stable
Classifier: Intended Audience :: Developers
Classifier: License :: OSI Approved :: MIT License
Classifier: Programming Language :: Python
Classifier: Programming Language :: Python :: 2.6
Classifier: Programming Language :: Python :: 2.7
Classifier: Programming Language :: Python :: 3
Classifier: Programming Language :: Python :: 3.3
Classifier: Programming Language :: Python :: 3.4
